[{"se":"A Frontier Scene","ep":"","sy":-2366737200,"ey":-2366737200},{"se":"Akrobatisches Potpourri","ep":"","sy":-2366737200,"ey":-2366737200},{"se":"Annabelle Serpentine Dance","ep":"","sy":-2366737200,"ey":-2366737200},{"se":"Apotheose","ep":"","sy":-2366737200,"ey":-2366737200},{"se":"Aquarium","ep":"","sy":-2366737200,"ey":-2366737200},{"se":"Archiv Skladanowsky","ep":"","sy":-2366737200,"ey":-2366737200},{"se":"Attilla No. 2","ep":"","sy":-2366737200,"ey":-2366737200},{"se":"Autour d'une cabine","ep":"","sy":-2366737200,"ey":-2366737200},{"se":"Baignade en mer","ep":"","sy":-2366737200,"ey":-2366737200},{"se":"Barque sortant du port","ep":"","sy":-2366737200,"ey":-2366737200},{"se":"Billy Edwards and the Unknown","ep":"","sy":-2366737200,"ey":-2366737200},{"se":"Bocal aux poissons-rouges","ep":"","sy":-2366737200,"ey":-2366737200},{"se":"Broadway, New York","ep":"","sy":-2366737200,"ey":-2366737200},{"se":"Charge of the Uhlans","ep":"","sy":-2366737200,"ey":-2366737200},{"se":"Chinese Laundry Scene","ep":"","sy":-2366737200,"ey":-2366737200},{"se":"Clovelly Cottage, Barnet","ep":"","sy":-2366737200,"ey":-2366737200},{"se":"Cricketer Jumping Over Garden Gate","ep":"","sy":-2366737200,"ey":-2366737200},{"se":"Cyclone Dance","ep":"","sy":-2366737200,"ey":-2366737200},{"se":"Dance of Rejoicing","ep":"","sy":-2366737200,"ey":-2366737200},{"se":"Der Jongleur","ep":"","sy":-2366737200,"ey":-2366737200},{"se":"Discussion de Monsieur Janssen et de Monsieur Lagrange","ep":"","sy":-2366737200,"ey":-2366737200},{"se":"Dr. Colton or Dentist Scene","ep":"","sy":-2366737200,"ey":-2366737200},{"se":"Duel Between Two Historical Characters","ep":"","sy":-2366737200,"ey":-2366737200},{"se":"Elevated Railway in the Streets of New York","ep":"","sy":-2366737200,"ey":-2366737200},{"se":"Elsie Jones","ep":"","sy":-2366737200,"ey":-2366737200},{"se":"Elsie Jones, No. 2","ep":"","sy":-2366737200,"ey":-2366737200},{"se":"Fan Dance","ep":"","sy":-2366737200,"ey":-2366737200},{"se":"German Emperor at Hamburg","ep":"","sy":-2366737200,"ey":-2366737200},{"se":"Gladiatorial Combat","ep":"","sy":-2366737200,"ey":-2366737200},{"se":"Grotesque Tumbling","ep":"","sy":-2366737200,"ey":-2366737200},{"se":"Grundy and Frint","ep":"","sy":-2366737200,"ey":-2366737200},{"se":"Highgate Tunnel: Goods Train","ep":"","sy":-2366737200,"ey":-2366737200},{"se":"Hindoostan Fakir and Cotta Dwarf","ep":"","sy":-2366737200,"ey":-2366737200},{"se":"Indian Scalping Scene","ep":"","sy":-2366737200,"ey":-2366737200},{"se":"Italienischer Bauerntanz","ep":"","sy":-2366737200,"ey":-2366737200},{"se":"James Grundy, Buck and Wing","ep":"","sy":-2366737200,"ey":-2366737200},{"se":"James Grundy, Cake Walk","ep":"","sy":-2366737200,"ey":-2366737200},{"se":"Joan of Arc","ep":"","sy":-2366737200,"ey":-2366737200},{"se":"John W. Wilson and Bertha Waring","ep":"","sy":-2366737200,"ey":-2366737200},{"se":"Kaiser-Parade auf dem Tempelhofer Felde","ep":"","sy":-2366737200,"ey":-2366737200},{"se":"Kamarinskaja","ep":"","sy":-2366737200,"ey":-2366737200},{"se":"Komisches Reck","ep":"","sy":-2366737200,"ey":-2366737200},{"se":"Krieger-Parade","ep":"","sy":-2366737200,"ey":-2366737200},{"se":"La mer par gros temps","ep":"","sy":-2366737200,"ey":-2366737200},{"se":"La voltige","ep":"","sy":-2366737200,"ey":-2366737200},{"se":"Laying the First Stone on Kaiser Wilhelm's Memorial","ep":"","sy":-2366737200,"ey":-2366737200},{"se":"Les bronzes font du surf","ep":"","sy":-2366737200,"ey":-2366737200},{"se":"Les forgerons","ep":"","sy":-2366737200,"ey":-2366737200},{"se":"Lyon, place Bellecour","ep":"","sy":-2366737200,"ey":-2366737200},{"se":"Muscle Dance","ep":"","sy":-2366737200,"ey":-2366737200},{"se":"New Bar Room","ep":"","sy":-2366737200,"ey":-2366737200},{"se":"New Barber's Shop","ep":"","sy":-2366737200,"ey":-2366737200},{"se":"New Blacksmith Shop","ep":"","sy":-2366737200,"ey":-2366737200},{"se":"Niagara Falls in Winter: The Waterfall","ep":"","sy":-2366737200,"ey":-2366737200},{"se":"Niagara Falls: Close to the Waterfall","ep":"","sy":-2366737200,"ey":-2366737200},{"se":"Niagara Falls: The Great Whirlpool","ep":"","sy":-2366737200,"ey":-2366737200},{"se":"Opening of the Kiel Canal","ep":"","sy":-2366737200,"ey":-2366737200},{"se":"Opera Scene","ep":"","sy":-2366737200,"ey":-2366737200},{"se":"Paddle Dance","ep":"","sy":-2366737200,"ey":-2366737200},{"se":"Parade der Veteranen des deutsch-franz Krieges","ep":"","sy":-2366737200,"ey":-2366737200},{"se":"Partie de tric-trac","ep":"","sy":-2366737200,"ey":-2366737200},{"se":"Photographe","ep":"","sy":-2366737200,"ey":-2366737200},{"se":"Pompiers: Attaque du feu","ep":"","sy":-2366737200,"ey":-2366737200},{"se":"Princess Ali","ep":"","sy":-2366737200,"ey":-2366737200},{"se":"Professor Attilla","ep":"","sy":-2366737200,"ey":-2366737200},{"se":"Quartette","ep":"","sy":-2366737200,"ey":-2366737200},{"se":"Rescue of Capt. John Smith by Pocahontas","ep":"","sy":-2366737200,"ey":-2366737200},{"se":"Rob Roy","ep":"","sy":-2366737200,"ey":-2366737200},{"se":"Robetta and Doretto, No. 1","ep":"","sy":-2366737200,"ey":-2366737200},{"se":"Robetta and Doretto, No. 3","ep":"","sy":-2366737200,"ey":-2366737200},{"se":"S.A.R. il Principe di Napoli e la Principessa Elena visitano il battistero di S. Giovanni a Firenze","ep":"","sy":-2366737200,"ey":-2366737200},{"se":"Schlusssteinlegung des Kaiser Wilhelm Kanals","ep":"","sy":-2366737200,"ey":-2366737200},{"se":"Shoeblack at Work in a London Street","ep":"","sy":-2366737200,"ey":-2366737200},{"se":"Short Stick Dance","ep":"","sy":-2366737200,"ey":-2366737200},{"se":"Silver Dance","ep":"","sy":-2366737200,"ey":-2366737200},{"se":"Smith and Machinery at Work","ep":"","sy":-2366737200,"ey":-2366737200},{"se":"Steam Yacht at the Canal Entrance","ep":"","sy":-2366737200,"ey":-2366737200},{"se":"Steamer 'New York' in Dock","ep":"","sy":-2366737200,"ey":-2366737200},{"se":"Steamer on Long Island Sound","ep":"","sy":-2366737200,"ey":-2366737200},{"se":"Street Scene in Winter in Montreal, Canada","ep":"","sy":-2366737200,"ey":-2366737200},{"se":"Suvier Entering the Baltic Canal, Hamburg","ep":"","sy":-2366737200,"ey":-2366737200},{"se":"The Arrest of a Bookmaker","ep":"","sy":-2366737200,"ey":-2366737200},{"se":"The Arrest of a Pickpocket","ep":"","sy":-2366737200,"ey":-2366737200},{"se":"The Derby 1895","ep":"","sy":-2366737200,"ey":-2366737200},{"se":"The Execution of Mary, Queen of Scots","ep":"","sy":-2366737200,"ey":-2366737200},{"se":"The Gay Brothers","ep":"","sy":-2366737200,"ey":-2366737200},{"se":"The German Emperor Reviewing His Troops","ep":"","sy":-2366737200,"ey":-2366737200},{"se":"The Oxford and Cambridge University Boat Race","ep":"","sy":-2366737200,"ey":-2366737200},{"se":"The Rixfords, No. 1","ep":"","sy":-2366737200,"ey":-2366737200},{"se":"The Rixfords, No. 2","ep":"","sy":-2366737200,"ey":-2366737200},{"se":"The Sausage Machine","ep":"","sy":-2366737200,"ey":-2366737200},{"se":"Tom Merry, Lightning Cartoonist","ep":"","sy":-2366737200,"ey":-2366737200},{"se":"Tom Merry, Lightning Cartoonist II","ep":"","sy":-2366737200,"ey":-2366737200},{"se":"Trilby Dance","ep":"","sy":-2366737200,"ey":-2366737200},{"se":"Trilby Death Scene","ep":"","sy":-2366737200,"ey":-2366737200},{"se":"Trilby Hypnotic Scene","ep":"","sy":-2366737200,"ey":-2366737200},{"se":"Umbrella Dance","ep":"","sy":-2366737200,"ey":-2366737200},{"se":"Untitled Kinetoscope Comedy","ep":"","sy":-2366737200,"ey":-2366737200},{"se":"Venice: The Rialto Bridge","ep":"","sy":-2366737200,"ey":-2366737200},{"se":"Wintergartenprogramm","ep":"","sy":-2366737200,"ey":-2366737200},{"se":"Young Griffo v. Battling Charles Barnett","ep":"","sy":-2366737200,"ey":-2366737200},{"se":"Young Weimer","ep":"","sy":-2366737200,"ey":-2366737200}]